.gitignore
COPYING
LICENSE
Makefile
README.md
distribute_setup.py
requirements.txt
setup.py
accuri2fcs/__init__.py
accuri2fcs/accuri2fcs.py
accuri2fcs.egg-info/PKG-INFO
accuri2fcs.egg-info/SOURCES.txt
accuri2fcs.egg-info/dependency_links.txt
accuri2fcs.egg-info/entry_points.txt
accuri2fcs.egg-info/top_level.txt