Metadata-Version: 1.1
Name: accuri2fcs
Version: 0.1.0
Summary: Convert Accuri format flow cytometry files to standard .fcs
Home-page: https://github.com/mfitzp/accura2fcs
Author: Martin Fitzpatrick
Author-email: martin.fitzpatrick@gmail.com
License: BSD
Download-URL: https://github.com/mfitzp/accura2fcs/zipball/master
Keywords: bioinformatics flow cytometry accuri facs research analysis science
Platform: UNKNOWN
Classifier: Development Status :: 4 - Beta
Classifier: Natural Language :: English
Classifier: Operating System :: OS Independent
Classifier: Programming Language :: Python :: 2
Classifier: License :: OSI Approved :: BSD License
Classifier: Topic :: Scientific/Engineering :: Bio-Informatics
Classifier: Topic :: Education
Classifier: Intended Audience :: Science/Research
Classifier: Intended Audience :: Education
